{"grimeSwatch": "85569834", "name": "wlv_mil_xanadu_falu", "emissiveAmount": 0.0, "swatches": [{"emissiveAmount": 0.0, "scratchRoughness": 1.0, "scratchBrightness": 0.0, "ior": 0.04, "colorVariant": {"botColor": [1.0, 1.0, 1.0], "id": "4B26CC91", "topColor": [0.2384, 0.2705, 0.2195], "midColor": [1.0, 1.0, 1.0]}, "normalPath": "materials\\generic\\base\\human\\paint\\painted_metal_scratched\\hum_base_painted_metal_scratched_normal", "normalTextureTransform": [2.0, 2.0], "scratchAlbedoTint": 0.0, "scratchColor": [0.3155, 0.3155, 0.3155], "metallic": 0.0, "scratchMetallic": 1.0, "roughnessBlack": 0.24, "colorVariantId": "4B26CC91", "scratchIor": 0.04, "roughnessWhite": 0.53, "roughness": 4, "groupName": "", "emissiveIntensity": 0.0, "colorGradientMap": "materials\\generic\\base\\human\\paint\\painted_metal_scratched\\hum_base_painted_metal_scratched_gradientmask", "swatchId": "71B22594"}, {"emissiveAmount": 0.0, "scratchRoughness": 1.0, "scratchBrightness": 0.0, "ior": 0.04, "colorVariant": {"botColor": [0.128, 0.0616, 0.0559], "id": "6D9FBF72", "topColor": [0.0296, 0.0421, 0.0333], "midColor": [0.1789, 0.0635, 0.0528]}, "normalPath": "materials\\generic\\base\\human\\paint\\painted_metal_scratched\\hum_base_painted_metal_scratched_normal", "normalTextureTransform": [2.0, 2.0], "scratchAlbedoTint": 0.0, "scratchColor": [0.3155, 0.3155, 0.3155], "metallic": 0.0, "scratchMetallic": 1.0, "roughnessBlack": 0.24, "colorVariantId": "6D9FBF72", "scratchIor": 0.04, "roughnessWhite": 0.53, "roughness": 4, "groupName": "", "emissiveIntensity": 0.0, "colorGradientMap": "materials\\generic\\base\\human\\paint\\painted_metal_scratched\\hum_base_painted_metal_scratched_gradientmask", "swatchId": "9E199922"}, {"emissiveAmount": 0.0, "scratchRoughness": 0.9, "scratchBrightness": 0.0, "ior": 0.04, "colorVariant": {"botColor": [0.0094, 0.0094, 0.0094], "id": "206A641D", "topColor": [0.0134, 0.0134, 0.0134], "midColor": [0.0137, 0.0137, 0.0137]}, "normalPath": "materials\\generic\\base\\organic\\dust\\org_base_dust_01_normal", "normalTextureTransform": [0.5, 0.5], "scratchAlbedoTint": 0.0, "scratchColor": [0.0242, 0.02, 0.0169], "metallic": 0.0, "scratchMetallic": 0.0, "roughnessBlack": 0.95, "colorVariantId": "206A641D", "scratchIor": 0.04, "roughnessWhite": 0.85, "roughness": 4, "groupName": "", "emissiveIntensity": 0.0, "colorGradientMap": "materials\\generic\\base\\organic\\dust\\org_base_dust_01_gradientmask", "swatchId": "85569834"}, {"emissiveAmount": 0.0, "scratchRoughness": 1.0, "scratchBrightness": 0.0, "ior": 0.04, "colorVariant": {"botColor": [1.0, 0.0054, 0.0], "id": "894F3E4F", "topColor": [0.4665, 0.6506, 0.5035], "midColor": [0.6506, 0.0043, 0.0]}, "normalPath": "materials\\generic\\base\\human\\paint\\painted_metal_scratched\\hum_base_painted_metal_scratched_normal", "normalTextureTransform": [2.0, 2.0], "scratchAlbedoTint": 0.0, "scratchColor": [0.3155, 0.3155, 0.3155], "metallic": 0.0, "scratchMetallic": 1.0, "roughnessBlack": 0.24, "colorVariantId": "894F3E4F", "scratchIor": 0.04, "roughnessWhite": 0.53, "roughness": 4, "groupName": "", "emissiveIntensity": 0.0, "colorGradientMap": "materials\\generic\\base\\human\\paint\\painted_metal_scratched\\hum_base_painted_metal_scratched_gradientmask", "swatchId": "A29B01FC"}, {"emissiveAmount": 1.0, "scratchRoughness": 0.5, "scratchBrightness": 0.0, "ior": 0.04, "colorVariant": {"botColor": [0.7484, 0.7484, 0.7484], "id": "AD681CE5", "topColor": [0.8276, 0.8276, 0.8276], "midColor": [0.8013, 0.8013, 0.8013]}, "normalPath": "materials\\generic\\base\\human\\glass\\visor\\hum_base_glass_visor_normal", "normalTextureTransform": [5.0, 5.0], "scratchAlbedoTint": 0.0, "scratchColor": [0.3185, 0.3185, 0.3185], "metallic": 1.0, "scratchMetallic": 1.0, "roughnessBlack": 0.06, "colorVariantId": "AD681CE5", "scratchIor": 0.04, "roughnessWhite": 0.07, "roughness": 4, "groupName": "", "emissiveIntensity": 0.5, "colorGradientMap": "materials\\generic\\base\\human\\glass\\visor\\hum_base_glass_visor_gradientmask", "swatchId": "7264002B"}, {"emissiveAmount": 0.0, "scratchRoughness": 1.0, "scratchBrightness": 0.0, "ior": 0.04, "colorVariant": {"botColor": [0.2961, 0.2307, 0.1248], "id": "A60D7D2A", "topColor": [0.9473, 0.7758, 0.3663], "midColor": [0.6172, 0.5149, 0.2664]}, "normalPath": "materials\\generic\\base\\human\\fabric\\gauze\\hum_base_fabric_gauze_normal", "normalTextureTransform": [2.0, 2.0], "scratchAlbedoTint": 0.0, "scratchColor": [0.0, 0.0, 0.0], "metallic": 0.0, "scratchMetallic": 0.0, "roughnessBlack": 0.77, "colorVariantId": "A60D7D2A", "scratchIor": 0.04, "roughnessWhite": 0.88, "roughness": 4, "groupName": "", "emissiveIntensity": 0.0, "colorGradientMap": "materials\\generic\\base\\human\\fabric\\gauze\\hum_base_fabric_gauze_gradientmask", "swatchId": "DAAE99EA"}, {"emissiveAmount": 0.0, "scratchRoughness": 1.0, "scratchBrightness": 0.0, "ior": 0.04, "colorVariant": {"botColor": [0.6866, 0.3295, 0.0979], "id": "0DED5878", "topColor": [0.9216, 0.552, 0.2016], "midColor": [0.7758, 0.3712, 0.1095]}, "normalPath": "materials\\generic\\base\\human\\metal\\gold_worn\\hum_base_metal_gold_worn_normal", "normalTextureTransform": [0.5, 0.5], "scratchAlbedoTint": 0.0, "scratchColor": [0.0, 0.0, 0.0], "metallic": 1.0, "scratchMetallic": 0.0, "roughnessBlack": 0.29, "colorVariantId": "0DED5878", "scratchIor": 0.04, "roughnessWhite": 0.51, "roughness": 4, "groupName": "", "emissiveIntensity": 0.0, "colorGradientMap": "materials\\generic\\base\\human\\metal\\gold_worn\\hum_base_metal_gold_worn_gradientmask", "swatchId": "FCCCE7E1"}, {"emissiveAmount": 0.0, "scratchRoughness": 1.0, "scratchBrightness": 0.0, "ior": 0.04, "colorVariant": {"botColor": [1.0, 0.9047, 0.5711], "id": "4CD039BF", "topColor": [0.1119, 0.0513, 0.0273], "midColor": [0.4397, 0.2016, 0.0802]}, "normalPath": "materials\\generic\\base\\human\\paint\\painted_metal_scratched\\hum_base_painted_metal_scratched_normal", "normalTextureTransform": [2.0, 2.0], "scratchAlbedoTint": 0.0, "scratchColor": [0.3155, 0.3155, 0.3155], "metallic": 0.0, "scratchMetallic": 1.0, "roughnessBlack": 0.24, "colorVariantId": "4CD039BF", "scratchIor": 0.04, "roughnessWhite": 0.53, "roughness": 4, "groupName": "", "emissiveIntensity": 0.0, "colorGradientMap": "materials\\generic\\base\\human\\paint\\painted_metal_scratched\\hum_base_painted_metal_scratched_gradientmask", "swatchId": "D4453D9E"}, {"emissiveAmount": 0.0, "scratchRoughness": 1.0, "scratchBrightness": 0.0, "ior": 0.04, "colorVariant": {"botColor": [0.2789, 0.3864, 0.3005], "id": "4A67D771", "topColor": [0.1559, 0.227, 0.1746], "midColor": [0.0762, 0.1119, 0.0865]}, "normalPath": "materials\\generic\\base\\human\\paint\\painted_metal_scratched\\hum_base_painted_metal_scratched_normal", "normalTextureTransform": [2.0, 2.0], "scratchAlbedoTint": 0.0, "scratchColor": [0.3155, 0.3155, 0.3155], "metallic": 0.0, "scratchMetallic": 1.0, "roughnessBlack": 0.24, "colorVariantId": "4A67D771", "scratchIor": 0.04, "roughnessWhite": 0.53, "roughness": 4, "groupName": "", "emissiveIntensity": 0.0, "colorGradientMap": "materials\\generic\\base\\human\\paint\\painted_metal_scratched\\hum_base_painted_metal_scratched_gradientmask", "swatchId": "A3B21F28"}, {"emissiveAmount": 0.0, "scratchRoughness": 0.8, "scratchBrightness": 0.0, "ior": 0.04, "colorVariant": {"botColor": [0.0272, 0.0272, 0.0272], "id": "9B7BC545", "topColor": [0.0497, 0.0497, 0.0497], "midColor": [0.0331, 0.0331, 0.0331]}, "normalPath": "materials\\generic\\base\\human\\rubber\\neoprene\\hum_base_rubber_neoprene_normal", "normalTextureTransform": [0.5, 0.5], "scratchAlbedoTint": 0.0, "scratchColor": [0.2206, 0.2027, 0.1839], "metallic": 0.0, "scratchMetallic": 0.0, "roughnessBlack": 0.34, "colorVariantId": "9B7BC545", "scratchIor": 0.04, "roughnessWhite": 0.7, "roughness": 4, "groupName": "", "emissiveIntensity": 0.0, "colorGradientMap": "materials\\generic\\base\\human\\rubber\\neoprene\\hum_base_rubber_neoprene_gradientmask", "swatchId": "C65CF7A5"}, {"emissiveAmount": 0.0, "scratchRoughness": 0.5, "scratchBrightness": 0.0, "ior": 0.04, "colorVariant": {"botColor": [0.036, 0.0074, 0.0074], "id": "2F3B0B06", "topColor": [0.0862, 0.0173, 0.0173], "midColor": [0.0819, 0.0075, 0.0075]}, "normalPath": "materials\\generic\\base\\human\\fabric\\linen_rough\\hum_base_linen_rough_normal", "normalTextureTransform": [0.5, 0.5], "scratchAlbedoTint": 0.0, "scratchColor": [0.4325, 0.3464, 0.2733], "metallic": 0.0, "scratchMetallic": 0.0, "roughnessBlack": 0.67, "colorVariantId": "2F3B0B06", "scratchIor": 0.04, "roughnessWhite": 0.94, "roughness": 4, "groupName": "", "emissiveIntensity": 0.0, "colorGradientMap": "materials\\generic\\base\\human\\fabric\\linen_rough\\hum_base_linen_rough_gradientmask", "swatchId": "C7004051"}, {"emissiveAmount": 0.0, "scratchRoughness": 0.8, "scratchBrightness": 0.0, "ior": 0.04, "colorVariant": {"botColor": [0.1329, 0.0049, 0.0049], "id": "494D9679", "topColor": [1.0, 0.0196, 0.0196], "midColor": [0.4995, 0.0117, 0.0117]}, "normalPath": "materials\\generic\\base\\human\\rubber\\neoprene\\hum_base_rubber_neoprene_normal", "normalTextureTransform": [0.5, 0.5], "scratchAlbedoTint": 0.0, "scratchColor": [0.2206, 0.2027, 0.1839], "metallic": 0.0, "scratchMetallic": 0.0, "roughnessBlack": 0.34, "colorVariantId": "494D9679", "scratchIor": 0.04, "roughnessWhite": 0.7, "roughness": 4, "groupName": "", "emissiveIntensity": 0.0, "colorGradientMap": "materials\\generic\\base\\human\\rubber\\neoprene\\hum_base_rubber_neoprene_gradientmask", "swatchId": "C903CF22"}, {"emissiveAmount": 0.0, "scratchRoughness": 0.8, "scratchBrightness": 0.0, "ior": 0.04, "colorVariant": {"botColor": [0.0063, 0.0063, 0.0063], "id": "13916E1B", "topColor": [0.0203, 0.0203, 0.0203], "midColor": [0.01, 0.01, 0.01]}, "normalPath": "materials\\generic\\base\\human\\rubber\\neoprene\\hum_base_rubber_neoprene_normal", "normalTextureTransform": [0.5, 0.5], "scratchAlbedoTint": 0.0, "scratchColor": [0.2206, 0.2027, 0.1839], "metallic": 0.0, "scratchMetallic": 0.0, "roughnessBlack": 0.34, "colorVariantId": "13916E1B", "scratchIor": 0.04, "roughnessWhite": 0.7, "roughness": 4, "groupName": "", "emissiveIntensity": 0.0, "colorGradientMap": "materials\\generic\\base\\human\\rubber\\neoprene\\hum_base_rubber_neoprene_gradientmask", "swatchId": "48805759"}, {"emissiveAmount": 0.0, "scratchRoughness": 0.5, "scratchBrightness": 0.0, "ior": 0.04, "colorVariant": {"botColor": [0.0292, 0.0234, 0.0191], "id": "024D22AC", "topColor": [0.0698, 0.0549, 0.0438], "midColor": [0.0482, 0.0382, 0.0307]}, "normalPath": "materials\\generic\\base\\human\\fabric\\linen_rough\\hum_base_linen_rough_normal", "normalTextureTransform": [0.5, 0.5], "scratchAlbedoTint": 0.0, "scratchColor": [0.4325, 0.3464, 0.2733], "metallic": 0.0, "scratchMetallic": 0.0, "roughnessBlack": 0.67, "colorVariantId": "024D22AC", "scratchIor": 0.04, "roughnessWhite": 0.94, "roughness": 4, "groupName": "", "emissiveIntensity": 0.0, "colorGradientMap": "materials\\generic\\base\\human\\fabric\\linen_rough\\hum_base_linen_rough_gradientmask", "swatchId": "53586300"}, {"emissiveAmount": 0.0, "scratchRoughness": 0.5, "scratchBrightness": 0.0, "ior": 0.04, "colorVariant": {"botColor": [0.0762, 0.1119, 0.0865], "id": "A0F314A3", "topColor": [0.2789, 0.3864, 0.3005], "midColor": [0.1559, 0.227, 0.1746]}, "normalPath": "materials\\generic\\base\\human\\fabric\\linen_rough\\hum_base_linen_rough_normal", "normalTextureTransform": [0.5, 0.5], "scratchAlbedoTint": 0.0, "scratchColor": [0.4325, 0.3464, 0.2733], "metallic": 0.0, "scratchMetallic": 0.0, "roughnessBlack": 0.67, "colorVariantId": "A0F314A3", "scratchIor": 0.04, "roughnessWhite": 0.94, "roughness": 4, "groupName": "", "emissiveIntensity": 0.0, "colorGradientMap": "materials\\generic\\base\\human\\fabric\\linen_rough\\hum_base_linen_rough_gradientmask", "swatchId": "F717F3CF"}, {"emissiveAmount": 0.0, "scratchRoughness": 0.5, "scratchBrightness": 0.0, "ior": 0.04, "colorVariant": {"botColor": [0.2384, 0.2705, 0.2195], "id": "2ECB3817", "topColor": [0.807, 0.8796, 0.8148], "midColor": [0.8963, 0.9823, 0.9047]}, "normalPath": "materials\\generic\\base\\human\\fabric\\linen_rough\\hum_base_linen_rough_normal", "normalTextureTransform": [0.5, 0.5], "scratchAlbedoTint": 0.0, "scratchColor": [0.4325, 0.3464, 0.2733], "metallic": 0.0, "scratchMetallic": 0.0, "roughnessBlack": 0.67, "colorVariantId": "2ECB3817", "scratchIor": 0.04, "roughnessWhite": 0.94, "roughness": 4, "groupName": "", "emissiveIntensity": 0.0, "colorGradientMap": "materials\\generic\\base\\human\\fabric\\linen_rough\\hum_base_linen_rough_gradientmask", "swatchId": "210F65AB"}, {"emissiveAmount": 0.0, "scratchRoughness": 0.9, "scratchBrightness": 0.0, "ior": 0.04, "colorVariant": {"botColor": [0.0203, 0.0133, 0.009], "id": "4626DD5E", "topColor": [0.0353, 0.0258, 0.0156], "midColor": [0.047, 0.0312, 0.0187]}, "normalPath": "materials\\generic\\base\\organic\\dust\\org_base_dust_01_normal", "normalTextureTransform": [0.5, 0.5], "scratchAlbedoTint": 0.0, "scratchColor": [0.0242, 0.02, 0.0169], "metallic": 0.0, "scratchMetallic": 0.0, "roughnessBlack": 0.95, "colorVariantId": "4626DD5E", "scratchIor": 0.04, "roughnessWhite": 0.85, "roughness": 4, "groupName": "", "emissiveIntensity": 0.0, "colorGradientMap": "materials\\generic\\base\\organic\\dust\\org_base_dust_01_gradientmask", "swatchId": "D03018C3"}, {"emissiveAmount": 0.0, "scratchRoughness": 1.0, "scratchBrightness": 0.0, "ior": 0.04, "colorVariant": {"botColor": [0.0033, 0.0033, 0.0033], "id": "586376C6", "topColor": [0.0033, 0.0033, 0.0033], "midColor": [0.0033, 0.0033, 0.0033]}, "normalPath": "materials\\generic\\base\\human\\glass\\opaque_glass\\hum_base_glass_opaque_normal", "normalTextureTransform": [0.5, 0.5], "scratchAlbedoTint": 1.0, "scratchColor": [0.0, 0.0, 0.0], "metallic": 0.0, "scratchMetallic": 0.0, "roughnessBlack": 0.9, "colorVariantId": "586376C6", "scratchIor": 0.04, "roughnessWhite": 1.0, "roughness": 4, "groupName": "", "emissiveIntensity": 0.0, "colorGradientMap": "materials\\generic\\base\\human\\glass\\opaque_glass\\hum_base_glass_opaque_gradientmask", "swatchId": "69DFBB74"}, {"emissiveAmount": 0.0, "scratchRoughness": 1.0, "scratchBrightness": 0.0, "ior": 0.04, "colorVariant": {"botColor": [0.0, 0.0, 0.0], "id": "192CB666", "topColor": [0.0, 0.0, 0.0], "midColor": [0.0, 0.0, 0.0]}, "normalPath": "shaders\\default_bitmaps\\bitmaps\\default_normal", "normalTextureTransform": [1.0, 1.0], "scratchAlbedoTint": 0.0, "scratchColor": [0.0, 0.0, 0.0], "metallic": 0.0, "scratchMetallic": 0.0, "roughnessBlack": 0.0, "colorVariantId": "192CB666", "scratchIor": 0.04, "roughnessWhite": 1.0, "roughness": 4, "groupName": "", "emissiveIntensity": 0.0, "colorGradientMap": "shaders\\default_bitmaps\\bitmaps\\color_black", "swatchId": "84FFA275"}, {"emissiveAmount": 0.0, "scratchRoughness": 1.0, "scratchBrightness": 0.0, "ior": 0.04, "colorVariant": {"botColor": [0.3278, 0.2874, 0.2122], "id": "20EFD87D", "topColor": [0.4969, 0.4179, 0.3419], "midColor": [0.4179, 0.3467, 0.2705]}, "normalPath": "materials\\generic\\base\\human\\organic\\bone\\hum_base_organic_bone_normal", "normalTextureTransform": [0.5, 0.5], "scratchAlbedoTint": 0.0, "scratchColor": [1.0, 1.0, 1.0], "metallic": 0.0, "scratchMetallic": 0.0, "roughnessBlack": 0.49, "colorVariantId": "20EFD87D", "scratchIor": 0.04, "roughnessWhite": 0.82, "roughness": 4, "groupName": "", "emissiveIntensity": 0.0, "colorGradientMap": "materials\\generic\\base\\human\\organic\\bone\\hum_base_organic_bone_gradientmask", "swatchId": "77A25222"}, {"emissiveAmount": 0.0, "scratchRoughness": 1.0, "scratchBrightness": 0.0, "ior": 0.04, "colorVariant": {"botColor": [0.0033, 0.0033, 0.0033], "id": "586376C6", "topColor": [0.0033, 0.0033, 0.0033], "midColor": [0.0033, 0.0033, 0.0033]}, "normalPath": "materials\\generic\\base\\human\\glass\\opaque_glass\\hum_base_glass_opaque_normal", "normalTextureTransform": [0.5, 0.5], "scratchAlbedoTint": 0.0, "scratchColor": [0.0, 0.0, 0.0], "metallic": 0.0, "scratchMetallic": 0.0, "roughnessBlack": 0.0, "colorVariantId": "586376C6", "scratchIor": 0.04, "roughnessWhite": 0.08, "roughness": 4, "groupName": "", "emissiveIntensity": 0.0, "colorGradientMap": "materials\\generic\\base\\human\\glass\\opaque_glass\\hum_base_glass_opaque_gradientmask", "swatchId": "26EE3995"}, {"emissiveAmount": 0.0, "scratchRoughness": 1.0, "scratchBrightness": 0.0, "ior": 0.04, "colorVariant": {"botColor": [0.8543, 0.8543, 0.8543], "id": "6B02C932", "topColor": [0.9266, 0.9266, 0.9266], "midColor": [0.7954, 0.7954, 0.7954]}, "normalPath": "materials\\generic\\base\\human\\glass\\opaque_glass\\hum_base_glass_opaque_normal", "normalTextureTransform": [0.5, 0.5], "scratchAlbedoTint": 0.0, "scratchColor": [0.0, 0.0, 0.0], "metallic": 0.0, "scratchMetallic": 0.0, "roughnessBlack": 0.0, "colorVariantId": "6B02C932", "scratchIor": 0.04, "roughnessWhite": 0.08, "roughness": 4, "groupName": "", "emissiveIntensity": 0.0, "colorGradientMap": "materials\\generic\\base\\human\\glass\\opaque_glass\\hum_base_glass_opaque_gradientmask", "swatchId": "09B6727A"}, {"emissiveAmount": 0.0, "scratchRoughness": 1.0, "scratchBrightness": 0.0, "ior": 0.04, "colorVariant": {"botColor": [0.0, 0.0, 0.0], "id": "192CB666", "topColor": [0.0, 0.0, 0.0], "midColor": [0.0, 0.0, 0.0]}, "normalPath": "shaders\\default_bitmaps\\bitmaps\\default_normal", "normalTextureTransform": [1.0, 1.0], "scratchAlbedoTint": 0.0, "scratchColor": [0.0, 0.0, 0.0], "metallic": 0.0, "scratchMetallic": 0.0, "roughnessBlack": 0.0, "colorVariantId": "192CB666", "scratchIor": 0.04, "roughnessWhite": 1.0, "roughness": 4, "groupName": "", "emissiveIntensity": 0.0, "colorGradientMap": "shaders\\default_bitmaps\\bitmaps\\color_black", "swatchId": "00000000"}], "grimeAmount": 0.8, "regionLayers": {"326D0638": {"layers": [{"colorBlend": true, "swatch": "69DFBB74", "ignoreTexelDensity": false, "normalBlend": false}], "material": "cvw_1_layered", "bodyPart": "326D0638"}, "r_kneepad": {"layers": [{"colorBlend": true, "swatch": "71B22594", "ignoreTexelDensity": false, "normalBlend": false}, {"colorBlend": true, "swatch": "48805759", "ignoreTexelDensity": false, "normalBlend": false}, {"colorBlend": true, "swatch": "84FFA275", "ignoreTexelDensity": false, "normalBlend": false}, {"colorBlend": true, "swatch": "84FFA275", "ignoreTexelDensity": false, "normalBlend": false}, {"colorBlend": true, "swatch": "C65CF7A5", "ignoreTexelDensity": false, "normalBlend": false}, {"colorBlend": true, "swatch": "53586300", "ignoreTexelDensity": false, "normalBlend": false}, {"colorBlend": true, "swatch": "D03018C3", "ignoreTexelDensity": false, "normalBlend": false}], "material": "cvw_7_layered", "bodyPart": "r_kneepad"}, "l_knee": {"layers": [{"colorBlend": true, "swatch": "F717F3CF", "ignoreTexelDensity": false, "normalBlend": false}, {"colorBlend": true, "swatch": "210F65AB", "ignoreTexelDensity": false, "normalBlend": false}, {"colorBlend": true, "swatch": "DAAE99EA", "ignoreTexelDensity": false, "normalBlend": false}, {"colorBlend": true, "swatch": "FCCCE7E1", "ignoreTexelDensity": false, "normalBlend": false}, {"colorBlend": true, "swatch": "84FFA275", "ignoreTexelDensity": false, "normalBlend": false}, {"colorBlend": true, "swatch": "84FFA275", "ignoreTexelDensity": false, "normalBlend": false}, {"colorBlend": true, "swatch": "D03018C3", "ignoreTexelDensity": false, "normalBlend": false}], "material": "cvw_7_layered", "bodyPart": "l_knee"}, "l_shoulderpad": {"layers": [{"colorBlend": true, "swatch": "D4453D9E", "ignoreTexelDensity": false, "normalBlend": false}, {"colorBlend": true, "swatch": "84FFA275", "ignoreTexelDensity": false, "normalBlend": false}, {"colorBlend": true, "swatch": "FCCCE7E1", "ignoreTexelDensity": false, "normalBlend": false}, {"colorBlend": true, "swatch": "53586300", "ignoreTexelDensity": false, "normalBlend": false}, {"colorBlend": true, "swatch": "84FFA275", "ignoreTexelDensity": false, "normalBlend": false}, {"colorBlend": true, "swatch": "84FFA275", "ignoreTexelDensity": false, "normalBlend": false}, {"colorBlend": true, "swatch": "D03018C3", "ignoreTexelDensity": false, "normalBlend": false}], "material": "cvw_7_layered", "bodyPart": "l_shoulderpad"}, "l_boot": {"layers": [{"colorBlend": true, "swatch": "9E199922", "ignoreTexelDensity": false, "normalBlend": false}, {"colorBlend": true, "swatch": "A29B01FC", "ignoreTexelDensity": false, "normalBlend": false}, {"colorBlend": true, "swatch": "DAAE99EA", "ignoreTexelDensity": false, "normalBlend": false}, {"colorBlend": true, "swatch": "DAAE99EA", "ignoreTexelDensity": false, "normalBlend": false}, {"colorBlend": true, "swatch": "53586300", "ignoreTexelDensity": false, "normalBlend": false}, {"colorBlend": true, "swatch": "A29B01FC", "ignoreTexelDensity": false, "normalBlend": false}, {"colorBlend": true, "swatch": "D03018C3", "ignoreTexelDensity": false, "normalBlend": false}], "material": "cvw_7_layered", "bodyPart": "l_boot"}, "r_boot": {"layers": [{"colorBlend": true, "swatch": "9E199922", "ignoreTexelDensity": false, "normalBlend": false}, {"colorBlend": true, "swatch": "A29B01FC", "ignoreTexelDensity": false, "normalBlend": false}, {"colorBlend": true, "swatch": "DAAE99EA", "ignoreTexelDensity": false, "normalBlend": false}, {"colorBlend": true, "swatch": "DAAE99EA", "ignoreTexelDensity": false, "normalBlend": false}, {"colorBlend": true, "swatch": "53586300", "ignoreTexelDensity": false, "normalBlend": false}, {"colorBlend": true, "swatch": "A29B01FC", "ignoreTexelDensity": false, "normalBlend": false}, {"colorBlend": true, "swatch": "D03018C3", "ignoreTexelDensity": false, "normalBlend": false}], "material": "cvw_7_layered", "bodyPart": "r_boot"}, "r_shoulderpad": {"layers": [{"colorBlend": true, "swatch": "9E199922", "ignoreTexelDensity": false, "normalBlend": false}, {"colorBlend": true, "swatch": "A29B01FC", "ignoreTexelDensity": false, "normalBlend": false}, {"colorBlend": true, "swatch": "A29B01FC", "ignoreTexelDensity": false, "normalBlend": false}, {"colorBlend": true, "swatch": "53586300", "ignoreTexelDensity": false, "normalBlend": false}, {"colorBlend": true, "swatch": "84FFA275", "ignoreTexelDensity": false, "normalBlend": false}, {"colorBlend": true, "swatch": "84FFA275", "ignoreTexelDensity": false, "normalBlend": false}, {"colorBlend": true, "swatch": "D03018C3", "ignoreTexelDensity": false, "normalBlend": false}], "material": "cvw_7_layered", "bodyPart": "r_shoulderpad"}, "helmet": {"layers": [{"colorBlend": true, "swatch": "A29B01FC", "ignoreTexelDensity": false, "normalBlend": false}, {"colorBlend": true, "swatch": "71B22594", "ignoreTexelDensity": false, "normalBlend": false}, {"colorBlend": true, "swatch": "9E199922", "ignoreTexelDensity": false, "normalBlend": false}, {"colorBlend": true, "swatch": "71B22594", "ignoreTexelDensity": false, "normalBlend": false}, {"colorBlend": true, "swatch": "DAAE99EA", "ignoreTexelDensity": false, "normalBlend": false}, {"colorBlend": true, "swatch": "71B22594", "ignoreTexelDensity": false, "normalBlend": false}, {"colorBlend": true, "swatch": "D03018C3", "ignoreTexelDensity": false, "normalBlend": false}], "material": "cvw_7_layered", "bodyPart": "helmet"}, "r_armfor": {"layers": [{"colorBlend": true, "swatch": "F717F3CF", "ignoreTexelDensity": false, "normalBlend": false}, {"colorBlend": true, "swatch": "D4453D9E", "ignoreTexelDensity": false, "normalBlend": false}, {"colorBlend": true, "swatch": "53586300", "ignoreTexelDensity": false, "normalBlend": false}, {"colorBlend": true, "swatch": "DAAE99EA", "ignoreTexelDensity": false, "normalBlend": false}, {"colorBlend": true, "swatch": "DAAE99EA", "ignoreTexelDensity": false, "normalBlend": false}, {"colorBlend": true, "swatch": "A3B21F28", "ignoreTexelDensity": false, "normalBlend": false}, {"colorBlend": true, "swatch": "D03018C3", "ignoreTexelDensity": false, "normalBlend": false}], "material": "cvw_7_layered", "bodyPart": "r_armfor"}, "r_shin": {"layers": [{"colorBlend": true, "swatch": "9E199922", "ignoreTexelDensity": false, "normalBlend": false}, {"colorBlend": true, "swatch": "84FFA275", "ignoreTexelDensity": false, "normalBlend": false}, {"colorBlend": true, "swatch": "53586300", "ignoreTexelDensity": false, "normalBlend": false}, {"colorBlend": true, "swatch": "84FFA275", "ignoreTexelDensity": false, "normalBlend": false}, {"colorBlend": true, "swatch": "DAAE99EA", "ignoreTexelDensity": false, "normalBlend": false}, {"colorBlend": true, "swatch": "F717F3CF", "ignoreTexelDensity": false, "normalBlend": false}, {"colorBlend": true, "swatch": "D03018C3", "ignoreTexelDensity": false, "normalBlend": false}], "material": "cvw_7_layered", "bodyPart": "r_shin"}, "r_glove": {"layers": [{"colorBlend": true, "swatch": "C7004051", "ignoreTexelDensity": false, "normalBlend": false}, {"colorBlend": true, "swatch": "DAAE99EA", "ignoreTexelDensity": false, "normalBlend": false}, {"colorBlend": true, "swatch": "48805759", "ignoreTexelDensity": false, "normalBlend": false}, {"colorBlend": true, "swatch": "FCCCE7E1", "ignoreTexelDensity": false, "normalBlend": false}, {"colorBlend": true, "swatch": "84FFA275", "ignoreTexelDensity": false, "normalBlend": false}, {"colorBlend": true, "swatch": "53586300", "ignoreTexelDensity": false, "normalBlend": false}, {"colorBlend": true, "swatch": "D03018C3", "ignoreTexelDensity": false, "normalBlend": false}], "material": "cvw_7_layered", "bodyPart": "r_glove"}, "l_kneepad": {"layers": [{"colorBlend": true, "swatch": "FCCCE7E1", "ignoreTexelDensity": false, "normalBlend": false}, {"colorBlend": true, "swatch": "48805759", "ignoreTexelDensity": false, "normalBlend": false}, {"colorBlend": true, "swatch": "84FFA275", "ignoreTexelDensity": false, "normalBlend": false}, {"colorBlend": true, "swatch": "84FFA275", "ignoreTexelDensity": false, "normalBlend": false}, {"colorBlend": true, "swatch": "C65CF7A5", "ignoreTexelDensity": false, "normalBlend": false}, {"colorBlend": true, "swatch": "53586300", "ignoreTexelDensity": false, "normalBlend": false}, {"colorBlend": true, "swatch": "D03018C3", "ignoreTexelDensity": false, "normalBlend": false}], "material": "cvw_7_layered", "bodyPart": "l_kneepad"}, "torso_belt": {"layers": [{"colorBlend": true, "swatch": "9E199922", "ignoreTexelDensity": false, "normalBlend": false}, {"colorBlend": true, "swatch": "FCCCE7E1", "ignoreTexelDensity": false, "normalBlend": false}, {"colorBlend": true, "swatch": "84FFA275", "ignoreTexelDensity": false, "normalBlend": false}, {"colorBlend": true, "swatch": "9E199922", "ignoreTexelDensity": false, "normalBlend": false}, {"colorBlend": true, "swatch": "FCCCE7E1", "ignoreTexelDensity": false, "normalBlend": false}, {"colorBlend": true, "swatch": "DAAE99EA", "ignoreTexelDensity": false, "normalBlend": false}, {"colorBlend": true, "swatch": "D03018C3", "ignoreTexelDensity": false, "normalBlend": false}], "material": "cvw_7_layered", "bodyPart": "torso_belt"}, "r_thigh": {"layers": [{"colorBlend": true, "swatch": "71B22594", "ignoreTexelDensity": false, "normalBlend": false}, {"colorBlend": true, "swatch": "210F65AB", "ignoreTexelDensity": false, "normalBlend": false}, {"colorBlend": true, "swatch": "A3B21F28", "ignoreTexelDensity": false, "normalBlend": false}, {"colorBlend": true, "swatch": "DAAE99EA", "ignoreTexelDensity": false, "normalBlend": false}, {"colorBlend": true, "swatch": "DAAE99EA", "ignoreTexelDensity": false, "normalBlend": false}, {"colorBlend": true, "swatch": "C903CF22", "ignoreTexelDensity": false, "normalBlend": false}, {"colorBlend": true, "swatch": "D03018C3", "ignoreTexelDensity": false, "normalBlend": false}], "material": "cvw_7_layered", "bodyPart": "r_thigh"}, "l_shin": {"layers": [{"colorBlend": true, "swatch": "9E199922", "ignoreTexelDensity": false, "normalBlend": false}, {"colorBlend": true, "swatch": "84FFA275", "ignoreTexelDensity": false, "normalBlend": false}, {"colorBlend": true, "swatch": "53586300", "ignoreTexelDensity": false, "normalBlend": false}, {"colorBlend": true, "swatch": "84FFA275", "ignoreTexelDensity": false, "normalBlend": false}, {"colorBlend": true, "swatch": "DAAE99EA", "ignoreTexelDensity": false, "normalBlend": false}, {"colorBlend": true, "swatch": "F717F3CF", "ignoreTexelDensity": false, "normalBlend": false}, {"colorBlend": true, "swatch": "D03018C3", "ignoreTexelDensity": false, "normalBlend": false}], "material": "cvw_7_layered", "bodyPart": "l_shin"}, "l_glove": {"layers": [{"colorBlend": true, "swatch": "9E199922", "ignoreTexelDensity": false, "normalBlend": false}, {"colorBlend": true, "swatch": "DAAE99EA", "ignoreTexelDensity": false, "normalBlend": false}, {"colorBlend": true, "swatch": "84FFA275", "ignoreTexelDensity": false, "normalBlend": false}, {"colorBlend": true, "swatch": "FCCCE7E1", "ignoreTexelDensity": false, "normalBlend": false}, {"colorBlend": true, "swatch": "84FFA275", "ignoreTexelDensity": false, "normalBlend": false}, {"colorBlend": true, "swatch": "53586300", "ignoreTexelDensity": false, "normalBlend": false}, {"colorBlend": true, "swatch": "D03018C3", "ignoreTexelDensity": false, "normalBlend": false}], "material": "cvw_7_layered", "bodyPart": "l_glove"}, "l_armup": {"layers": [{"colorBlend": true, "swatch": "C7004051", "ignoreTexelDensity": false, "normalBlend": false}, {"colorBlend": true, "swatch": "A29B01FC", "ignoreTexelDensity": false, "normalBlend": false}, {"colorBlend": true, "swatch": "53586300", "ignoreTexelDensity": false, "normalBlend": false}, {"colorBlend": true, "swatch": "FCCCE7E1", "ignoreTexelDensity": false, "normalBlend": false}, {"colorBlend": true, "swatch": "FCCCE7E1", "ignoreTexelDensity": false, "normalBlend": false}, {"colorBlend": true, "swatch": "C903CF22", "ignoreTexelDensity": false, "normalBlend": false}, {"colorBlend": true, "swatch": "D03018C3", "ignoreTexelDensity": false, "normalBlend": false}], "material": "cvw_7_layered", "bodyPart": "l_armup"}, "l_armfor": {"layers": [{"colorBlend": true, "swatch": "F717F3CF", "ignoreTexelDensity": false, "normalBlend": false}, {"colorBlend": true, "swatch": "D4453D9E", "ignoreTexelDensity": false, "normalBlend": false}, {"colorBlend": true, "swatch": "53586300", "ignoreTexelDensity": false, "normalBlend": false}, {"colorBlend": true, "swatch": "DAAE99EA", "ignoreTexelDensity": false, "normalBlend": false}, {"colorBlend": true, "swatch": "DAAE99EA", "ignoreTexelDensity": false, "normalBlend": false}, {"colorBlend": true, "swatch": "A3B21F28", "ignoreTexelDensity": false, "normalBlend": false}, {"colorBlend": true, "swatch": "D03018C3", "ignoreTexelDensity": false, "normalBlend": false}], "material": "cvw_7_layered", "bodyPart": "l_armfor"}, "l_thigh": {"layers": [{"colorBlend": true, "swatch": "71B22594", "ignoreTexelDensity": false, "normalBlend": false}, {"colorBlend": true, "swatch": "210F65AB", "ignoreTexelDensity": false, "normalBlend": false}, {"colorBlend": true, "swatch": "A3B21F28", "ignoreTexelDensity": false, "normalBlend": false}, {"colorBlend": true, "swatch": "DAAE99EA", "ignoreTexelDensity": false, "normalBlend": false}, {"colorBlend": true, "swatch": "DAAE99EA", "ignoreTexelDensity": false, "normalBlend": false}, {"colorBlend": true, "swatch": "C903CF22", "ignoreTexelDensity": false, "normalBlend": false}, {"colorBlend": true, "swatch": "D03018C3", "ignoreTexelDensity": false, "normalBlend": false}], "material": "cvw_7_layered", "bodyPart": "l_thigh"}, "neck": {"layers": [{"colorBlend": true, "swatch": "C903CF22", "ignoreTexelDensity": false, "normalBlend": false}, {"colorBlend": true, "swatch": "84FFA275", "ignoreTexelDensity": false, "normalBlend": false}, {"colorBlend": true, "swatch": "84FFA275", "ignoreTexelDensity": false, "normalBlend": false}, {"colorBlend": true, "swatch": "D03018C3", "ignoreTexelDensity": false, "normalBlend": false}], "material": "cvw_4_layered", "bodyPart": "neck"}, "mp_visor": {"layers": [{"colorBlend": true, "swatch": "7264002B", "ignoreTexelDensity": false, "normalBlend": false}], "material": "cvw_1_layered", "bodyPart": "mp_visor"}, "r_armup": {"layers": [{"colorBlend": true, "swatch": "C7004051", "ignoreTexelDensity": false, "normalBlend": false}, {"colorBlend": true, "swatch": "A29B01FC", "ignoreTexelDensity": false, "normalBlend": false}, {"colorBlend": true, "swatch": "53586300", "ignoreTexelDensity": false, "normalBlend": false}, {"colorBlend": true, "swatch": "FCCCE7E1", "ignoreTexelDensity": false, "normalBlend": false}, {"colorBlend": true, "swatch": "FCCCE7E1", "ignoreTexelDensity": false, "normalBlend": false}, {"colorBlend": true, "swatch": "C903CF22", "ignoreTexelDensity": false, "normalBlend": false}, {"colorBlend": true, "swatch": "D03018C3", "ignoreTexelDensity": false, "normalBlend": false}], "material": "cvw_7_layered", "bodyPart": "r_armup"}, "torso": {"layers": [{"colorBlend": true, "swatch": "A29B01FC", "ignoreTexelDensity": false, "normalBlend": false}, {"colorBlend": true, "swatch": "210F65AB", "ignoreTexelDensity": false, "normalBlend": false}, {"colorBlend": true, "swatch": "C7004051", "ignoreTexelDensity": false, "normalBlend": false}, {"colorBlend": true, "swatch": "C65CF7A5", "ignoreTexelDensity": false, "normalBlend": false}, {"colorBlend": true, "swatch": "FCCCE7E1", "ignoreTexelDensity": false, "normalBlend": false}, {"colorBlend": true, "swatch": "C903CF22", "ignoreTexelDensity": false, "normalBlend": false}, {"colorBlend": true, "swatch": "D03018C3", "ignoreTexelDensity": false, "normalBlend": false}], "material": "cvw_7_layered", "bodyPart": "torso"}, "r_knee": {"layers": [{"colorBlend": true, "swatch": "F717F3CF", "ignoreTexelDensity": false, "normalBlend": false}, {"colorBlend": true, "swatch": "210F65AB", "ignoreTexelDensity": false, "normalBlend": false}, {"colorBlend": true, "swatch": "DAAE99EA", "ignoreTexelDensity": false, "normalBlend": false}, {"colorBlend": true, "swatch": "FCCCE7E1", "ignoreTexelDensity": false, "normalBlend": false}, {"colorBlend": true, "swatch": "84FFA275", "ignoreTexelDensity": false, "normalBlend": false}, {"colorBlend": true, "swatch": "84FFA275", "ignoreTexelDensity": false, "normalBlend": false}, {"colorBlend": true, "swatch": "D03018C3", "ignoreTexelDensity": false, "normalBlend": false}], "material": "cvw_7_layered", "bodyPart": "r_knee"}, "1B61B6F2": {"layers": [{"colorBlend": true, "swatch": "09B6727A", "ignoreTexelDensity": false, "normalBlend": false}], "material": "cvw_1_layered_alpha", "bodyPart": "1B61B6F2"}, "C1E58CB9": {"layers": [{"colorBlend": true, "swatch": "71B22594", "ignoreTexelDensity": false, "normalBlend": false}, {"colorBlend": true, "swatch": "D4453D9E", "ignoreTexelDensity": false, "normalBlend": false}, {"colorBlend": true, "swatch": "9E199922", "ignoreTexelDensity": false, "normalBlend": false}, {"colorBlend": true, "swatch": "26EE3995", "ignoreTexelDensity": false, "normalBlend": false}, {"colorBlend": true, "swatch": "A3B21F28", "ignoreTexelDensity": false, "normalBlend": false}, {"colorBlend": true, "swatch": "DAAE99EA", "ignoreTexelDensity": false, "normalBlend": false}, {"colorBlend": true, "swatch": "D03018C3", "ignoreTexelDensity": false, "normalBlend": false}], "material": "cvw_7_layered", "bodyPart": "C1E58CB9"}, "r_shoulderpad_legendary": {"layers": [{"colorBlend": true, "swatch": "77A25222", "ignoreTexelDensity": false, "normalBlend": false}, {"colorBlend": true, "swatch": "53586300", "ignoreTexelDensity": false, "normalBlend": false}, {"colorBlend": true, "swatch": "FCCCE7E1", "ignoreTexelDensity": false, "normalBlend": false}, {"colorBlend": true, "swatch": "C903CF22", "ignoreTexelDensity": false, "normalBlend": false}, {"colorBlend": true, "swatch": "71B22594", "ignoreTexelDensity": false, "normalBlend": false}, {"colorBlend": true, "swatch": "DAAE99EA", "ignoreTexelDensity": false, "normalBlend": false}, {"colorBlend": true, "swatch": "85569834", "ignoreTexelDensity": false, "normalBlend": false}], "material": "cvw_7_layered", "bodyPart": "r_shoulderpad_legendary"}, "l_shoulderpad_legendary": {"layers": [{"colorBlend": true, "swatch": "77A25222", "ignoreTexelDensity": false, "normalBlend": false}, {"colorBlend": true, "swatch": "53586300", "ignoreTexelDensity": false, "normalBlend": false}, {"colorBlend": true, "swatch": "FCCCE7E1", "ignoreTexelDensity": false, "normalBlend": false}, {"colorBlend": true, "swatch": "C903CF22", "ignoreTexelDensity": false, "normalBlend": false}, {"colorBlend": true, "swatch": "71B22594", "ignoreTexelDensity": false, "normalBlend": false}, {"colorBlend": true, "swatch": "DAAE99EA", "ignoreTexelDensity": false, "normalBlend": false}, {"colorBlend": true, "swatch": "85569834", "ignoreTexelDensity": false, "normalBlend": false}], "material": "cvw_7_layered", "bodyPart": "l_shoulderpad_legendary"}}, "scratchAmount": 0.75}