{"grimeSwatch": "32FDFBB4", "name": "oly_mil_gunsmoke_gold", "emissiveAmount": 0.0, "swatches": [{"emissiveAmount": 0.0, "scratchRoughness": 1.0, "scratchBrightness": 0.0, "ior": 0.04, "colorVariant": {"botColor": [0.0, 0.0, 0.0], "id": "192CB666", "topColor": [0.0, 0.0, 0.0], "midColor": [0.0, 0.0, 0.0]}, "normalPath": "shaders\\default_bitmaps\\bitmaps\\default_normal", "normalTextureTransform": [1.0, 1.0], "scratchAlbedoTint": 0.0, "scratchColor": [0.0, 0.0, 0.0], "metallic": 0.0, "scratchMetallic": 0.0, "roughnessBlack": 0.0, "colorVariantId": "192CB666", "scratchIor": 0.04, "roughnessWhite": 1.0, "roughness": 4, "groupName": "", "emissiveIntensity": 0.0, "colorGradientMap": "shaders\\default_bitmaps\\bitmaps\\color_black", "swatchId": "1F732BDB"}, {"emissiveAmount": 0.0, "scratchRoughness": 0.5, "scratchBrightness": 0.0, "ior": 0.04, "colorVariant": {"botColor": [0.0276, 0.0149, 0.0024], "id": "B52180E6", "topColor": [0.1556, 0.0345, 0.0073], "midColor": [0.0889, 0.0548, 0.0071]}, "normalPath": "materials\\generic\\base\\human\\glass\\visor\\hum_base_glass_visor_normal", "normalTextureTransform": [5.0, 5.0], "scratchAlbedoTint": 0.0, "scratchColor": [0.3185, 0.3185, 0.3185], "metallic": 1.0, "scratchMetallic": 1.0, "roughnessBlack": 0.06, "colorVariantId": "B52180E6", "scratchIor": 0.04, "roughnessWhite": 0.07, "roughness": 8, "groupName": "", "emissiveIntensity": 0.0, "colorGradientMap": "materials\\generic\\base\\human\\glass\\visor\\hum_base_glass_visor_gradientmask", "swatchId": "4E7F1D50"}, {"emissiveAmount": 0.0, "scratchRoughness": 0.4, "scratchBrightness": 0.0, "ior": 0.04, "colorVariant": {"botColor": [0.099, 0.1317, 0.1666], "id": "0FD55376", "topColor": [0.1873, 0.2669, 0.328], "midColor": [0.1281, 0.1783, 0.2159]}, "normalPath": "materials\\generic\\base\\human\\paint\\metal_smooth\\hum_base_paint_metal_smooth_normal", "normalTextureTransform": [1.0, 1.0], "scratchAlbedoTint": 0.0, "scratchColor": [0.196, 0.1901, 0.1815], "metallic": 0.0, "scratchMetallic": 1.0, "roughnessBlack": 0.22, "colorVariantId": "0FD55376", "scratchIor": 0.04, "roughnessWhite": 0.47, "roughness": 8, "groupName": "", "emissiveIntensity": 0.0, "colorGradientMap": "materials\\generic\\base\\human\\paint\\metal_smooth\\hum_base_paint_metal_smooth_gradientmask", "swatchId": "12C0A00F"}, {"emissiveAmount": 0.0, "scratchRoughness": 0.65, "scratchBrightness": 0.0, "ior": 0.04, "colorVariant": {"botColor": [0.1912, 0.1912, 0.1912], "id": "2C82F310", "topColor": [0.3005, 0.3005, 0.3005], "midColor": [0.2747, 0.2747, 0.2747]}, "normalPath": "materials\\generic\\base\\human\\metal\\steel_scratched\\hum_base_metal_steel_scratched_normal", "normalTextureTransform": [1.0, 1.0], "scratchAlbedoTint": 0.0, "scratchColor": [0.3749, 0.3749, 0.3749], "metallic": 1.0, "scratchMetallic": 1.0, "roughnessBlack": 0.4, "colorVariantId": "2C82F310", "scratchIor": 0.04, "roughnessWhite": 0.79, "roughness": 0, "groupName": "", "emissiveIntensity": 0.0, "colorGradientMap": "materials\\generic\\base\\human\\metal\\steel_scratched\\hum_base_metal_steel_scratched_gradientmask", "swatchId": "AB2E7D5B"}, {"emissiveAmount": 0.0, "scratchRoughness": 0.8, "scratchBrightness": 0.0, "ior": 0.04, "colorVariant": {"botColor": [0.0999, 0.1329, 0.1651], "id": "A05A3A02", "topColor": [0.1878, 0.2664, 0.3278], "midColor": [0.1274, 0.1779, 0.2159]}, "normalPath": "materials\\generic\\base\\human\\rubber\\hard\\hum_base_rubber_hard_normal", "normalTextureTransform": [0.5, 0.5], "scratchAlbedoTint": 0.0, "scratchColor": [0.1329, 0.1329, 0.1329], "metallic": 0.0, "scratchMetallic": 0.0, "roughnessBlack": 0.31, "colorVariantId": "A05A3A02", "scratchIor": 0.04, "roughnessWhite": 0.4, "roughness": 4, "groupName": "", "emissiveIntensity": 0.0, "colorGradientMap": "materials\\generic\\base\\human\\rubber\\hard\\hum_base_rubber_hard_gradientmask", "swatchId": "446523DB"}, {"emissiveAmount": 0.0, "scratchRoughness": 0.8, "scratchBrightness": 0.0, "ior": 0.04, "colorVariant": {"botColor": [0.1301, 0.0529, 0.011], "id": "C5BB3475", "topColor": [0.2582, 0.1329, 0.063], "midColor": [0.3419, 0.1144, 0.0284]}, "normalPath": "materials\\generic\\base\\human\\fabric\\neoprene_mesh\\hum_base_fabric_neoprene_mesh_normal", "normalTextureTransform": [1.0, 1.0], "scratchAlbedoTint": 0.0, "scratchColor": [0.1329, 0.1329, 0.1329], "metallic": 0.0, "scratchMetallic": 0.0, "roughnessBlack": 0.55, "colorVariantId": "C5BB3475", "scratchIor": 0.04, "roughnessWhite": 0.71, "roughness": 4, "groupName": "", "emissiveIntensity": 0.0, "colorGradientMap": "materials\\generic\\base\\human\\fabric\\neoprene_mesh\\hum_base_fabric_neoprene_mesh_gradientmask", "swatchId": "43841A29"}, {"emissiveAmount": 0.0, "scratchRoughness": 0.9, "scratchBrightness": 0.0, "ior": 0.04, "colorVariant": {"botColor": [0.031, 0.0177, 0.0065], "id": "666B4E1C", "topColor": [0.055, 0.0323, 0.0127], "midColor": [0.0497, 0.025, 0.0074]}, "normalPath": "materials\\generic\\base\\organic\\dust\\org_base_dust_01_normal", "normalTextureTransform": [0.5, 0.5], "scratchAlbedoTint": 0.0, "scratchColor": [0.0242, 0.02, 0.0169], "metallic": 0.0, "scratchMetallic": 0.0, "roughnessBlack": 0.95, "colorVariantId": "666B4E1C", "scratchIor": 0.04, "roughnessWhite": 0.85, "roughness": 4, "groupName": "", "emissiveIntensity": 0.0, "colorGradientMap": "materials\\generic\\base\\organic\\dust\\org_base_dust_01_gradientmask", "swatchId": "B7052A62"}, {"emissiveAmount": 0.0, "scratchRoughness": 0.9, "scratchBrightness": 0.0, "ior": 0.04, "colorVariant": {"botColor": [0.0094, 0.0094, 0.0094], "id": "206A641D", "topColor": [0.0134, 0.0134, 0.0134], "midColor": [0.0137, 0.0137, 0.0137]}, "normalPath": "materials\\generic\\base\\organic\\dust\\org_base_dust_01_normal", "normalTextureTransform": [0.5, 0.5], "scratchAlbedoTint": 0.0, "scratchColor": [0.0242, 0.02, 0.0169], "metallic": 0.0, "scratchMetallic": 0.0, "roughnessBlack": 0.95, "colorVariantId": "206A641D", "scratchIor": 0.04, "roughnessWhite": 0.85, "roughness": 4, "groupName": "", "emissiveIntensity": 0.0, "colorGradientMap": "materials\\generic\\base\\organic\\dust\\org_base_dust_01_gradientmask", "swatchId": "32FDFBB4"}, {"emissiveAmount": 0.0, "scratchRoughness": 0.4, "scratchBrightness": 0.0, "ior": 0.04, "colorVariant": {"botColor": [0.2439, 0.1912, 0.1365], "id": "D19470B9", "topColor": [0.3814, 0.3048, 0.197], "midColor": [0.351, 0.2881, 0.1973]}, "normalPath": "materials\\generic\\base\\human\\paint\\metal_smooth\\hum_base_paint_metal_smooth_normal", "normalTextureTransform": [1.0, 1.0], "scratchAlbedoTint": 0.0, "scratchColor": [0.196, 0.1901, 0.1815], "metallic": 0.0, "scratchMetallic": 1.0, "roughnessBlack": 0.22, "colorVariantId": "D19470B9", "scratchIor": 0.04, "roughnessWhite": 0.47, "roughness": 8, "groupName": "", "emissiveIntensity": 0.0, "colorGradientMap": "materials\\generic\\base\\human\\paint\\metal_smooth\\hum_base_paint_metal_smooth_gradientmask", "swatchId": "9C8BF2BF"}, {"emissiveAmount": 0.0, "scratchRoughness": 0.8, "scratchBrightness": 0.0, "ior": 0.04, "colorVariant": {"botColor": [0.1706, 0.1352, 0.0799], "id": "60DE232C", "topColor": [0.314, 0.2462, 0.1441], "midColor": [0.1511, 0.1148, 0.0647]}, "normalPath": "materials\\generic\\base\\human\\rubber\\hard\\hum_base_rubber_hard_normal", "normalTextureTransform": [0.5, 0.5], "scratchAlbedoTint": 0.0, "scratchColor": [0.1329, 0.1329, 0.1329], "metallic": 0.0, "scratchMetallic": 0.0, "roughnessBlack": 0.31, "colorVariantId": "60DE232C", "scratchIor": 0.04, "roughnessWhite": 0.4, "roughness": 4, "groupName": "", "emissiveIntensity": 0.0, "colorGradientMap": "materials\\generic\\base\\human\\rubber\\hard\\hum_base_rubber_hard_gradientmask", "swatchId": "17179ADC"}, {"emissiveAmount": 0.0, "scratchRoughness": 0.8, "scratchBrightness": 0.0, "ior": 0.04, "colorVariant": {"botColor": [0.2423, 0.1912, 0.1119], "id": "53DC1DF5", "topColor": [0.314, 0.2462, 0.1441], "midColor": [0.227, 0.1714, 0.0953]}, "normalPath": "materials\\generic\\base\\human\\fabric\\neoprene\\hum_base_fabric_neoprene_normal", "normalTextureTransform": [0.5, 0.5], "scratchAlbedoTint": 0.0, "scratchColor": [0.214, 0.214, 0.214], "metallic": 0.0, "scratchMetallic": 0.0, "roughnessBlack": 0.55, "colorVariantId": "53DC1DF5", "scratchIor": 0.04, "roughnessWhite": 0.71, "roughness": 4, "groupName": "", "emissiveIntensity": 0.0, "colorGradientMap": "materials\\generic\\base\\human\\fabric\\neoprene\\hum_base_fabric_neoprene_gradientmask", "swatchId": "9E95CC7E"}, {"emissiveAmount": 0.0, "scratchRoughness": 0.8, "scratchBrightness": 0.0, "ior": 0.04, "colorVariant": {"botColor": [0.1301, 0.0529, 0.011], "id": "FA5CB1CD", "topColor": [0.2582, 0.1329, 0.063], "midColor": [0.3419, 0.1144, 0.0284]}, "normalPath": "materials\\generic\\base\\human\\rubber\\hard\\hum_base_rubber_hard_normal", "normalTextureTransform": [0.5, 0.5], "scratchAlbedoTint": 0.0, "scratchColor": [0.1329, 0.1329, 0.1329], "metallic": 0.0, "scratchMetallic": 0.0, "roughnessBlack": 0.31, "colorVariantId": "FA5CB1CD", "scratchIor": 0.04, "roughnessWhite": 0.4, "roughness": 4, "groupName": "", "emissiveIntensity": 0.0, "colorGradientMap": "materials\\generic\\base\\human\\rubber\\hard\\hum_base_rubber_hard_gradientmask", "swatchId": "AA6E1788"}, {"emissiveAmount": 0.0, "scratchRoughness": 0.4, "scratchBrightness": 0.0, "ior": 0.04, "colorVariant": {"botColor": [0.1301, 0.0529, 0.011], "id": "DAE4434F", "topColor": [0.2582, 0.1329, 0.063], "midColor": [0.3419, 0.1144, 0.0284]}, "normalPath": "materials\\generic\\base\\human\\paint\\metal_smooth\\hum_base_paint_metal_smooth_normal", "normalTextureTransform": [1.0, 1.0], "scratchAlbedoTint": 0.0, "scratchColor": [0.196, 0.1901, 0.1815], "metallic": 0.0, "scratchMetallic": 1.0, "roughnessBlack": 0.22, "colorVariantId": "DAE4434F", "scratchIor": 0.04, "roughnessWhite": 0.47, "roughness": 0, "groupName": "", "emissiveIntensity": 0.0, "colorGradientMap": "materials\\generic\\base\\human\\paint\\metal_smooth\\hum_base_paint_metal_smooth_gradientmask", "swatchId": "8FDE3E71"}, {"emissiveAmount": 0.0, "scratchRoughness": 0.4, "scratchBrightness": 0.0, "ior": 0.04, "colorVariant": {"botColor": [0.4132, 0.2007, 0.011], "id": "360955F5", "topColor": [1.0, 0.6428, 0.0993], "midColor": [0.6867, 0.3231, 0.0356]}, "normalPath": "materials\\generic\\base\\human\\paint\\metal_smooth\\hum_base_paint_metal_smooth_normal", "normalTextureTransform": [1.0, 1.0], "scratchAlbedoTint": 0.0, "scratchColor": [0.196, 0.1901, 0.1815], "metallic": 0.0, "scratchMetallic": 1.0, "roughnessBlack": 0.22, "colorVariantId": "360955F5", "scratchIor": 0.04, "roughnessWhite": 0.47, "roughness": 0, "groupName": "", "emissiveIntensity": 0.0, "colorGradientMap": "materials\\generic\\base\\human\\paint\\metal_smooth\\hum_base_paint_metal_smooth_gradientmask", "swatchId": "E564ED7C"}, {"emissiveAmount": 0.0, "scratchRoughness": 1.0, "scratchBrightness": 0.0, "ior": 0.04, "colorVariant": {"botColor": [0.0, 0.0, 0.0], "id": "192CB666", "topColor": [0.0, 0.0, 0.0], "midColor": [0.0, 0.0, 0.0]}, "normalPath": "shaders\\default_bitmaps\\bitmaps\\default_normal", "normalTextureTransform": [1.0, 1.0], "scratchAlbedoTint": 0.0, "scratchColor": [0.0, 0.0, 0.0], "metallic": 0.0, "scratchMetallic": 0.0, "roughnessBlack": 0.0, "colorVariantId": "192CB666", "scratchIor": 0.04, "roughnessWhite": 1.0, "roughness": 4, "groupName": "", "emissiveIntensity": 0.0, "colorGradientMap": "shaders\\default_bitmaps\\bitmaps\\color_black", "swatchId": "00000000"}], "grimeAmount": 0.85, "regionLayers": {"helmet": {"layers": [{"colorBlend": true, "swatch": "12C0A00F", "ignoreTexelDensity": false, "normalBlend": false}, {"colorBlend": true, "swatch": "E564ED7C", "ignoreTexelDensity": false, "normalBlend": false}, {"colorBlend": true, "swatch": "E564ED7C", "ignoreTexelDensity": false, "normalBlend": false}, {"colorBlend": true, "swatch": "E564ED7C", "ignoreTexelDensity": false, "normalBlend": false}, {"colorBlend": true, "swatch": "446523DB", "ignoreTexelDensity": false, "normalBlend": false}, {"colorBlend": true, "swatch": "1F732BDB", "ignoreTexelDensity": false, "normalBlend": false}, {"colorBlend": true, "swatch": "B7052A62", "ignoreTexelDensity": false, "normalBlend": false}], "material": "cvw_7_layered", "bodyPart": "helmet"}, "torso_belt": {"layers": [{"colorBlend": true, "swatch": "AA6E1788", "ignoreTexelDensity": false, "normalBlend": false}, {"colorBlend": true, "swatch": "9C8BF2BF", "ignoreTexelDensity": false, "normalBlend": false}, {"colorBlend": true, "swatch": "AB2E7D5B", "ignoreTexelDensity": false, "normalBlend": false}, {"colorBlend": true, "swatch": "446523DB", "ignoreTexelDensity": false, "normalBlend": false}, {"colorBlend": true, "swatch": "AB2E7D5B", "ignoreTexelDensity": false, "normalBlend": false}, {"colorBlend": true, "swatch": "AB2E7D5B", "ignoreTexelDensity": false, "normalBlend": false}, {"colorBlend": true, "swatch": "B7052A62", "ignoreTexelDensity": false, "normalBlend": false}], "material": "cvw_7_layered", "bodyPart": "torso_belt"}, "l_thigh": {"layers": [{"colorBlend": true, "swatch": "9C8BF2BF", "ignoreTexelDensity": false, "normalBlend": false}, {"colorBlend": true, "swatch": "1F732BDB", "ignoreTexelDensity": false, "normalBlend": false}, {"colorBlend": true, "swatch": "1F732BDB", "ignoreTexelDensity": false, "normalBlend": false}, {"colorBlend": true, "swatch": "17179ADC", "ignoreTexelDensity": false, "normalBlend": false}, {"colorBlend": true, "swatch": "1F732BDB", "ignoreTexelDensity": false, "normalBlend": false}, {"colorBlend": true, "swatch": "12C0A00F", "ignoreTexelDensity": false, "normalBlend": false}, {"colorBlend": true, "swatch": "B7052A62", "ignoreTexelDensity": false, "normalBlend": false}], "material": "cvw_7_layered", "bodyPart": "l_thigh"}, "r_shoulderpad_legendary": {"layers": [{"colorBlend": true, "swatch": "12C0A00F", "ignoreTexelDensity": false, "normalBlend": false}, {"colorBlend": true, "swatch": "E564ED7C", "ignoreTexelDensity": false, "normalBlend": false}, {"colorBlend": true, "swatch": "AB2E7D5B", "ignoreTexelDensity": false, "normalBlend": false}, {"colorBlend": true, "swatch": "E564ED7C", "ignoreTexelDensity": false, "normalBlend": false}, {"colorBlend": true, "swatch": "1F732BDB", "ignoreTexelDensity": false, "normalBlend": false}, {"colorBlend": true, "swatch": "1F732BDB", "ignoreTexelDensity": false, "normalBlend": false}, {"colorBlend": true, "swatch": "B7052A62", "ignoreTexelDensity": false, "normalBlend": false}], "material": "cvw_4_layered_damage", "bodyPart": "r_shoulderpad_legendary"}, "l_knee": {"layers": [{"colorBlend": true, "swatch": "9E95CC7E", "ignoreTexelDensity": false, "normalBlend": false}, {"colorBlend": true, "swatch": "17179ADC", "ignoreTexelDensity": false, "normalBlend": false}, {"colorBlend": true, "swatch": "9C8BF2BF", "ignoreTexelDensity": false, "normalBlend": false}, {"colorBlend": true, "swatch": "B7052A62", "ignoreTexelDensity": false, "normalBlend": false}], "material": "cvw_4_layered", "bodyPart": "l_knee"}, "l_shoulderpad": {"layers": [{"colorBlend": true, "swatch": "12C0A00F", "ignoreTexelDensity": false, "normalBlend": false}, {"colorBlend": true, "swatch": "E564ED7C", "ignoreTexelDensity": false, "normalBlend": false}, {"colorBlend": true, "swatch": "E564ED7C", "ignoreTexelDensity": false, "normalBlend": false}, {"colorBlend": true, "swatch": "8FDE3E71", "ignoreTexelDensity": false, "normalBlend": false}, {"colorBlend": true, "swatch": "1F732BDB", "ignoreTexelDensity": false, "normalBlend": false}, {"colorBlend": true, "swatch": "1F732BDB", "ignoreTexelDensity": false, "normalBlend": false}, {"colorBlend": true, "swatch": "B7052A62", "ignoreTexelDensity": false, "normalBlend": false}], "material": "cvw_7_layered", "bodyPart": "l_shoulderpad"}, "l_boot": {"layers": [{"colorBlend": true, "swatch": "8FDE3E71", "ignoreTexelDensity": false, "normalBlend": false}, {"colorBlend": true, "swatch": "12C0A00F", "ignoreTexelDensity": false, "normalBlend": false}, {"colorBlend": true, "swatch": "12C0A00F", "ignoreTexelDensity": false, "normalBlend": false}, {"colorBlend": true, "swatch": "AB2E7D5B", "ignoreTexelDensity": false, "normalBlend": false}, {"colorBlend": true, "swatch": "43841A29", "ignoreTexelDensity": false, "normalBlend": false}, {"colorBlend": true, "swatch": "9E95CC7E", "ignoreTexelDensity": false, "normalBlend": false}, {"colorBlend": true, "swatch": "B7052A62", "ignoreTexelDensity": false, "normalBlend": false}], "material": "cvw_7_layered", "bodyPart": "l_boot"}, "r_boot": {"layers": [{"colorBlend": true, "swatch": "8FDE3E71", "ignoreTexelDensity": false, "normalBlend": false}, {"colorBlend": true, "swatch": "12C0A00F", "ignoreTexelDensity": false, "normalBlend": false}, {"colorBlend": true, "swatch": "12C0A00F", "ignoreTexelDensity": false, "normalBlend": false}, {"colorBlend": true, "swatch": "AB2E7D5B", "ignoreTexelDensity": false, "normalBlend": false}, {"colorBlend": true, "swatch": "43841A29", "ignoreTexelDensity": false, "normalBlend": false}, {"colorBlend": true, "swatch": "9E95CC7E", "ignoreTexelDensity": false, "normalBlend": false}, {"colorBlend": true, "swatch": "B7052A62", "ignoreTexelDensity": false, "normalBlend": false}], "material": "cvw_7_layered", "bodyPart": "r_boot"}, "r_armfor": {"layers": [{"colorBlend": true, "swatch": "12C0A00F", "ignoreTexelDensity": false, "normalBlend": false}, {"colorBlend": true, "swatch": "43841A29", "ignoreTexelDensity": false, "normalBlend": false}, {"colorBlend": true, "swatch": "1F732BDB", "ignoreTexelDensity": false, "normalBlend": false}, {"colorBlend": true, "swatch": "8FDE3E71", "ignoreTexelDensity": false, "normalBlend": false}, {"colorBlend": true, "swatch": "AB2E7D5B", "ignoreTexelDensity": false, "normalBlend": false}, {"colorBlend": true, "swatch": "9E95CC7E", "ignoreTexelDensity": false, "normalBlend": false}, {"colorBlend": true, "swatch": "B7052A62", "ignoreTexelDensity": false, "normalBlend": false}], "material": "cvw_7_layered", "bodyPart": "r_armfor"}, "r_shin": {"layers": [{"colorBlend": true, "swatch": "12C0A00F", "ignoreTexelDensity": false, "normalBlend": false}, {"colorBlend": true, "swatch": "AB2E7D5B", "ignoreTexelDensity": false, "normalBlend": false}, {"colorBlend": true, "swatch": "1F732BDB", "ignoreTexelDensity": false, "normalBlend": false}, {"colorBlend": true, "swatch": "1F732BDB", "ignoreTexelDensity": false, "normalBlend": false}, {"colorBlend": true, "swatch": "AB2E7D5B", "ignoreTexelDensity": false, "normalBlend": false}, {"colorBlend": true, "swatch": "43841A29", "ignoreTexelDensity": false, "normalBlend": false}, {"colorBlend": true, "swatch": "B7052A62", "ignoreTexelDensity": false, "normalBlend": false}], "material": "cvw_7_layered", "bodyPart": "r_shin"}, "r_glove": {"layers": [{"colorBlend": true, "swatch": "17179ADC", "ignoreTexelDensity": false, "normalBlend": false}, {"colorBlend": true, "swatch": "9E95CC7E", "ignoreTexelDensity": false, "normalBlend": false}, {"colorBlend": true, "swatch": "AA6E1788", "ignoreTexelDensity": false, "normalBlend": false}, {"colorBlend": true, "swatch": "43841A29", "ignoreTexelDensity": false, "normalBlend": false}, {"colorBlend": true, "swatch": "AB2E7D5B", "ignoreTexelDensity": false, "normalBlend": false}, {"colorBlend": true, "swatch": "12C0A00F", "ignoreTexelDensity": false, "normalBlend": false}, {"colorBlend": true, "swatch": "B7052A62", "ignoreTexelDensity": false, "normalBlend": false}], "material": "cvw_7_layered", "bodyPart": "r_glove"}, "l_kneepad": {"layers": [{"colorBlend": true, "swatch": "E564ED7C", "ignoreTexelDensity": false, "normalBlend": false}, {"colorBlend": true, "swatch": "1F732BDB", "ignoreTexelDensity": false, "normalBlend": false}, {"colorBlend": true, "swatch": "17179ADC", "ignoreTexelDensity": false, "normalBlend": false}, {"colorBlend": true, "swatch": "B7052A62", "ignoreTexelDensity": false, "normalBlend": false}], "material": "cvw_4_layered", "bodyPart": "l_kneepad"}, "r_shoulderpad": {"layers": [{"colorBlend": true, "swatch": "12C0A00F", "ignoreTexelDensity": false, "normalBlend": false}, {"colorBlend": true, "swatch": "E564ED7C", "ignoreTexelDensity": false, "normalBlend": false}, {"colorBlend": true, "swatch": "E564ED7C", "ignoreTexelDensity": false, "normalBlend": false}, {"colorBlend": true, "swatch": "8FDE3E71", "ignoreTexelDensity": false, "normalBlend": false}, {"colorBlend": true, "swatch": "1F732BDB", "ignoreTexelDensity": false, "normalBlend": false}, {"colorBlend": true, "swatch": "1F732BDB", "ignoreTexelDensity": false, "normalBlend": false}, {"colorBlend": true, "swatch": "B7052A62", "ignoreTexelDensity": false, "normalBlend": false}], "material": "cvw_7_layered", "bodyPart": "r_shoulderpad"}, "r_thigh": {"layers": [{"colorBlend": true, "swatch": "9C8BF2BF", "ignoreTexelDensity": false, "normalBlend": false}, {"colorBlend": true, "swatch": "1F732BDB", "ignoreTexelDensity": false, "normalBlend": false}, {"colorBlend": true, "swatch": "1F732BDB", "ignoreTexelDensity": false, "normalBlend": false}, {"colorBlend": true, "swatch": "17179ADC", "ignoreTexelDensity": false, "normalBlend": false}, {"colorBlend": true, "swatch": "1F732BDB", "ignoreTexelDensity": false, "normalBlend": false}, {"colorBlend": true, "swatch": "12C0A00F", "ignoreTexelDensity": false, "normalBlend": false}, {"colorBlend": true, "swatch": "B7052A62", "ignoreTexelDensity": false, "normalBlend": false}], "material": "cvw_7_layered", "bodyPart": "r_thigh"}, "r_glove_legendary": {"layers": [{"colorBlend": true, "swatch": "17179ADC", "ignoreTexelDensity": false, "normalBlend": false}, {"colorBlend": true, "swatch": "9E95CC7E", "ignoreTexelDensity": false, "normalBlend": false}, {"colorBlend": true, "swatch": "AA6E1788", "ignoreTexelDensity": false, "normalBlend": false}, {"colorBlend": true, "swatch": "43841A29", "ignoreTexelDensity": false, "normalBlend": false}, {"colorBlend": true, "swatch": "AB2E7D5B", "ignoreTexelDensity": false, "normalBlend": false}, {"colorBlend": true, "swatch": "E564ED7C", "ignoreTexelDensity": false, "normalBlend": false}, {"colorBlend": true, "swatch": "B7052A62", "ignoreTexelDensity": false, "normalBlend": false}], "material": "cvw_7_layered", "bodyPart": "r_glove_legendary"}, "l_glove_legendary": {"layers": [{"colorBlend": true, "swatch": "17179ADC", "ignoreTexelDensity": false, "normalBlend": false}, {"colorBlend": true, "swatch": "9E95CC7E", "ignoreTexelDensity": false, "normalBlend": false}, {"colorBlend": true, "swatch": "AA6E1788", "ignoreTexelDensity": false, "normalBlend": false}, {"colorBlend": true, "swatch": "43841A29", "ignoreTexelDensity": false, "normalBlend": false}, {"colorBlend": true, "swatch": "AB2E7D5B", "ignoreTexelDensity": false, "normalBlend": false}, {"colorBlend": true, "swatch": "E564ED7C", "ignoreTexelDensity": false, "normalBlend": false}, {"colorBlend": true, "swatch": "B7052A62", "ignoreTexelDensity": false, "normalBlend": false}], "material": "cvw_7_layered", "bodyPart": "l_glove_legendary"}, "l_shin": {"layers": [{"colorBlend": true, "swatch": "12C0A00F", "ignoreTexelDensity": false, "normalBlend": false}, {"colorBlend": true, "swatch": "AB2E7D5B", "ignoreTexelDensity": false, "normalBlend": false}, {"colorBlend": true, "swatch": "1F732BDB", "ignoreTexelDensity": false, "normalBlend": false}, {"colorBlend": true, "swatch": "1F732BDB", "ignoreTexelDensity": false, "normalBlend": false}, {"colorBlend": true, "swatch": "AB2E7D5B", "ignoreTexelDensity": false, "normalBlend": false}, {"colorBlend": true, "swatch": "43841A29", "ignoreTexelDensity": false, "normalBlend": false}, {"colorBlend": true, "swatch": "B7052A62", "ignoreTexelDensity": false, "normalBlend": false}], "material": "cvw_7_layered", "bodyPart": "l_shin"}, "l_glove": {"layers": [{"colorBlend": true, "swatch": "17179ADC", "ignoreTexelDensity": false, "normalBlend": false}, {"colorBlend": true, "swatch": "9E95CC7E", "ignoreTexelDensity": false, "normalBlend": false}, {"colorBlend": true, "swatch": "AA6E1788", "ignoreTexelDensity": false, "normalBlend": false}, {"colorBlend": true, "swatch": "43841A29", "ignoreTexelDensity": false, "normalBlend": false}, {"colorBlend": true, "swatch": "AB2E7D5B", "ignoreTexelDensity": false, "normalBlend": false}, {"colorBlend": true, "swatch": "12C0A00F", "ignoreTexelDensity": false, "normalBlend": false}, {"colorBlend": true, "swatch": "B7052A62", "ignoreTexelDensity": false, "normalBlend": false}], "material": "cvw_7_layered", "bodyPart": "l_glove"}, "l_armup": {"layers": [{"colorBlend": true, "swatch": "9C8BF2BF", "ignoreTexelDensity": false, "normalBlend": false}, {"colorBlend": true, "swatch": "8FDE3E71", "ignoreTexelDensity": false, "normalBlend": false}, {"colorBlend": true, "swatch": "9E95CC7E", "ignoreTexelDensity": false, "normalBlend": false}, {"colorBlend": true, "swatch": "AB2E7D5B", "ignoreTexelDensity": false, "normalBlend": false}, {"colorBlend": true, "swatch": "AB2E7D5B", "ignoreTexelDensity": false, "normalBlend": false}, {"colorBlend": true, "swatch": "9E95CC7E", "ignoreTexelDensity": false, "normalBlend": false}, {"colorBlend": true, "swatch": "B7052A62", "ignoreTexelDensity": false, "normalBlend": false}], "material": "cvw_7_layered", "bodyPart": "l_armup"}, "l_armfor": {"layers": [{"colorBlend": true, "swatch": "12C0A00F", "ignoreTexelDensity": false, "normalBlend": false}, {"colorBlend": true, "swatch": "43841A29", "ignoreTexelDensity": false, "normalBlend": false}, {"colorBlend": true, "swatch": "1F732BDB", "ignoreTexelDensity": false, "normalBlend": false}, {"colorBlend": true, "swatch": "8FDE3E71", "ignoreTexelDensity": false, "normalBlend": false}, {"colorBlend": true, "swatch": "AB2E7D5B", "ignoreTexelDensity": false, "normalBlend": false}, {"colorBlend": true, "swatch": "9E95CC7E", "ignoreTexelDensity": false, "normalBlend": false}, {"colorBlend": true, "swatch": "B7052A62", "ignoreTexelDensity": false, "normalBlend": false}], "material": "cvw_7_layered", "bodyPart": "l_armfor"}, "r_kneepad": {"layers": [{"colorBlend": true, "swatch": "E564ED7C", "ignoreTexelDensity": false, "normalBlend": false}, {"colorBlend": true, "swatch": "1F732BDB", "ignoreTexelDensity": false, "normalBlend": false}, {"colorBlend": true, "swatch": "17179ADC", "ignoreTexelDensity": false, "normalBlend": false}, {"colorBlend": true, "swatch": "B7052A62", "ignoreTexelDensity": false, "normalBlend": false}], "material": "cvw_4_layered", "bodyPart": "r_kneepad"}, "l_shoulderpad_legendary": {"layers": [{"colorBlend": true, "swatch": "12C0A00F", "ignoreTexelDensity": false, "normalBlend": false}, {"colorBlend": true, "swatch": "E564ED7C", "ignoreTexelDensity": false, "normalBlend": false}, {"colorBlend": true, "swatch": "AB2E7D5B", "ignoreTexelDensity": false, "normalBlend": false}, {"colorBlend": true, "swatch": "E564ED7C", "ignoreTexelDensity": false, "normalBlend": false}, {"colorBlend": true, "swatch": "1F732BDB", "ignoreTexelDensity": false, "normalBlend": false}, {"colorBlend": true, "swatch": "1F732BDB", "ignoreTexelDensity": false, "normalBlend": false}, {"colorBlend": true, "swatch": "B7052A62", "ignoreTexelDensity": false, "normalBlend": false}], "material": "cvw_4_layered_damage", "bodyPart": "l_shoulderpad_legendary"}, "neck": {"layers": [{"colorBlend": true, "swatch": "9E95CC7E", "ignoreTexelDensity": false, "normalBlend": false}, {"colorBlend": true, "swatch": "446523DB", "ignoreTexelDensity": false, "normalBlend": false}, {"colorBlend": true, "swatch": "446523DB", "ignoreTexelDensity": false, "normalBlend": false}, {"colorBlend": true, "swatch": "B7052A62", "ignoreTexelDensity": false, "normalBlend": false}], "material": "cvw_4_layered", "bodyPart": "neck"}, "mp_visor": {"layers": [{"colorBlend": true, "swatch": "4E7F1D50", "ignoreTexelDensity": false, "normalBlend": false}], "material": "cvw_1_layered", "bodyPart": "mp_visor"}, "r_armup": {"layers": [{"colorBlend": true, "swatch": "9C8BF2BF", "ignoreTexelDensity": false, "normalBlend": false}, {"colorBlend": true, "swatch": "8FDE3E71", "ignoreTexelDensity": false, "normalBlend": false}, {"colorBlend": true, "swatch": "9E95CC7E", "ignoreTexelDensity": false, "normalBlend": false}, {"colorBlend": true, "swatch": "AB2E7D5B", "ignoreTexelDensity": false, "normalBlend": false}, {"colorBlend": true, "swatch": "AB2E7D5B", "ignoreTexelDensity": false, "normalBlend": false}, {"colorBlend": true, "swatch": "9E95CC7E", "ignoreTexelDensity": false, "normalBlend": false}, {"colorBlend": true, "swatch": "B7052A62", "ignoreTexelDensity": false, "normalBlend": false}], "material": "cvw_7_layered", "bodyPart": "r_armup"}, "torso": {"layers": [{"colorBlend": true, "swatch": "12C0A00F", "ignoreTexelDensity": false, "normalBlend": false}, {"colorBlend": true, "swatch": "E564ED7C", "ignoreTexelDensity": false, "normalBlend": false}, {"colorBlend": true, "swatch": "9E95CC7E", "ignoreTexelDensity": false, "normalBlend": false}, {"colorBlend": true, "swatch": "446523DB", "ignoreTexelDensity": false, "normalBlend": false}, {"colorBlend": true, "swatch": "AB2E7D5B", "ignoreTexelDensity": false, "normalBlend": false}, {"colorBlend": true, "swatch": "E564ED7C", "ignoreTexelDensity": false, "normalBlend": false}, {"colorBlend": true, "swatch": "B7052A62", "ignoreTexelDensity": false, "normalBlend": false}], "material": "cvw_7_layered", "bodyPart": "torso"}, "r_knee": {"layers": [{"colorBlend": true, "swatch": "9E95CC7E", "ignoreTexelDensity": false, "normalBlend": false}, {"colorBlend": true, "swatch": "17179ADC", "ignoreTexelDensity": false, "normalBlend": false}, {"colorBlend": true, "swatch": "9C8BF2BF", "ignoreTexelDensity": false, "normalBlend": false}, {"colorBlend": true, "swatch": "B7052A62", "ignoreTexelDensity": false, "normalBlend": false}], "material": "cvw_4_layered", "bodyPart": "r_knee"}}, "scratchAmount": 0.8}